sufast/__init__.py
sufast/core.py
sufast/sufast_server.dll
sufast/sufast_server.so
sufast-0.2.4.dist-info/LICENSE
sufast-0.2.4.dist-info/METADATA
sufast-0.2.4.dist-info/WHEEL
sufast-0.2.4.dist-info/top_level.txt
sufast-0.2.4.dist-info/RECORD
