Metadata-Version: 2.1
Name: sufast
Version: 0.2.4
Summary: A blazing-fast Python web framework powered by Rust 🚀
Home-page: https://github.com/shohan-dev/sufast
Author: Shohan
Author-email: shohan.dev.cse@gmail.com
License: MIT
Project-URL: Bug Tracker, https://github.com/shohan-dev/sufast/issues
Project-URL: Documentation, https://sufast.shohan.dev
Classifier: Programming Language :: Python :: 3
Classifier: License :: OSI Approved :: MIT License
Classifier: Operating System :: OS Independent
Classifier: Intended Audience :: Developers
Classifier: Topic :: Software Development :: Libraries :: Python Modules
Classifier: Topic :: Internet :: WWW/HTTP
Classifier: Development Status :: 3 - Alpha
Requires-Python: >=3.8
License-File: LICENSE
